{
  "version": {
    "fullVersion": "2.1.1",
    "major": "2",
    "minor": "1",
    "patch": "1"
  },
  "meta": {
    "flags": [
      "experimentalData"
    ]
  },
  "collections": [
    {
      "name": "page",
      "label": "Pages",
      "path": "content/pages",
      "format": "md",
      "ui": {},
      "fields": [
        {
          "type": "string",
          "name": "title",
          "label": "Page Title",
          "isTitle": true,
          "required": true,
          "description": "Used for the browser tab title and SEO.",
          "namespace": [
            "page",
            "title"
          ],
          "searchable": true,
          "uid": false
        },
        {
          "type": "object",
          "list": true,
          "name": "blocks",
          "label": "Sections",
          "templates": [
            {
              "name": "hero",
              "label": "Hero",
              "fields": [
                {
                  "type": "string",
                  "name": "headline",
                  "label": "Headline",
                  "namespace": [
                    "page",
                    "blocks",
                    "hero",
                    "headline"
                  ],
                  "searchable": true,
                  "uid": false
                },
                {
                  "type": "string",
                  "name": "subtext",
                  "label": "Subtext",
                  "ui": {
                    "component": "textarea"
                  },
                  "namespace": [
                    "page",
                    "blocks",
                    "hero",
                    "subtext"
                  ],
                  "searchable": true,
                  "uid": false
                },
                {
                  "type": "image",
                  "name": "backgroundImage",
                  "label": "Background Image",
                  "namespace": [
                    "page",
                    "blocks",
                    "hero",
                    "backgroundImage"
                  ],
                  "searchable": false,
                  "uid": false
                },
                {
                  "type": "object",
                  "name": "cta",
                  "label": "CTA Button",
                  "fields": [
                    {
                      "type": "string",
                      "name": "label",
                      "label": "Label",
                      "namespace": [
                        "page",
                        "blocks",
                        "hero",
                        "cta",
                        "label"
                      ]
                    },
                    {
                      "type": "string",
                      "name": "url",
                      "label": "URL",
                      "namespace": [
                        "page",
                        "blocks",
                        "hero",
                        "cta",
                        "url"
                      ]
                    }
                  ],
                  "namespace": [
                    "page",
                    "blocks",
                    "hero",
                    "cta"
                  ],
                  "searchable": true,
                  "uid": false
                }
              ],
              "namespace": [
                "page",
                "blocks",
                "hero"
              ]
            },
            {
              "name": "mission",
              "label": "Mission / Content",
              "fields": [
                {
                  "type": "image",
                  "name": "image",
                  "label": "Image",
                  "namespace": [
                    "page",
                    "blocks",
                    "mission",
                    "image"
                  ],
                  "searchable": false,
                  "uid": false
                },
                {
                  "type": "string",
                  "name": "imageSide",
                  "label": "Image Side",
                  "options": [
                    "left",
                    "right"
                  ],
                  "ui": {
                    "defaultValue": "left"
                  },
                  "namespace": [
                    "page",
                    "blocks",
                    "mission",
                    "imageSide"
                  ],
                  "searchable": true,
                  "uid": false
                },
                {
                  "type": "rich-text",
                  "name": "content",
                  "label": "Content",
                  "namespace": [
                    "page",
                    "blocks",
                    "mission",
                    "content"
                  ],
                  "searchable": true,
                  "parser": {
                    "type": "markdown"
                  },
                  "uid": false
                }
              ],
              "namespace": [
                "page",
                "blocks",
                "mission"
              ]
            },
            {
              "name": "impactGrid",
              "label": "Impact Grid",
              "fields": [
                {
                  "type": "object",
                  "list": true,
                  "name": "stats",
                  "label": "Stats",
                  "ui": {},
                  "fields": [
                    {
                      "type": "string",
                      "name": "value",
                      "label": "Value (e.g. 50)",
                      "namespace": [
                        "page",
                        "blocks",
                        "impactGrid",
                        "stats",
                        "value"
                      ]
                    },
                    {
                      "type": "string",
                      "name": "label",
                      "label": "Label (e.g. Dogs Saved)",
                      "namespace": [
                        "page",
                        "blocks",
                        "impactGrid",
                        "stats",
                        "label"
                      ]
                    }
                  ],
                  "namespace": [
                    "page",
                    "blocks",
                    "impactGrid",
                    "stats"
                  ],
                  "searchable": true,
                  "uid": false
                }
              ],
              "namespace": [
                "page",
                "blocks",
                "impactGrid"
              ]
            },
            {
              "name": "donation",
              "label": "Donation Info",
              "fields": [
                {
                  "type": "boolean",
                  "name": "visible",
                  "label": "Show Section",
                  "description": "Toggle to show/hide this section",
                  "namespace": [
                    "page",
                    "blocks",
                    "donation",
                    "visible"
                  ],
                  "searchable": true,
                  "uid": false
                },
                {
                  "type": "string",
                  "name": "headline",
                  "label": "Headline",
                  "namespace": [
                    "page",
                    "blocks",
                    "donation",
                    "headline"
                  ],
                  "searchable": true,
                  "uid": false
                },
                {
                  "type": "rich-text",
                  "name": "description",
                  "label": "Description",
                  "namespace": [
                    "page",
                    "blocks",
                    "donation",
                    "description"
                  ],
                  "searchable": true,
                  "parser": {
                    "type": "markdown"
                  },
                  "uid": false
                },
                {
                  "type": "object",
                  "list": true,
                  "name": "methods",
                  "label": "Donation Methods",
                  "ui": {},
                  "fields": [
                    {
                      "type": "string",
                      "name": "label",
                      "label": "Label (e.g. MBWay)",
                      "namespace": [
                        "page",
                        "blocks",
                        "donation",
                        "methods",
                        "label"
                      ]
                    },
                    {
                      "type": "string",
                      "name": "value",
                      "label": "Value (e.g. 912...)",
                      "namespace": [
                        "page",
                        "blocks",
                        "donation",
                        "methods",
                        "value"
                      ]
                    },
                    {
                      "type": "string",
                      "name": "helperText",
                      "label": "Helper Text (optional)",
                      "namespace": [
                        "page",
                        "blocks",
                        "donation",
                        "methods",
                        "helperText"
                      ]
                    }
                  ],
                  "namespace": [
                    "page",
                    "blocks",
                    "donation",
                    "methods"
                  ],
                  "searchable": true,
                  "uid": false
                }
              ],
              "namespace": [
                "page",
                "blocks",
                "donation"
              ]
            },
            {
              "name": "events",
              "label": "Events List",
              "fields": [
                {
                  "type": "object",
                  "list": true,
                  "name": "items",
                  "label": "Events",
                  "ui": {},
                  "fields": [
                    {
                      "type": "string",
                      "name": "title",
                      "label": "Event Title",
                      "namespace": [
                        "page",
                        "blocks",
                        "events",
                        "items",
                        "title"
                      ]
                    },
                    {
                      "type": "datetime",
                      "name": "date",
                      "label": "Date",
                      "namespace": [
                        "page",
                        "blocks",
                        "events",
                        "items",
                        "date"
                      ]
                    },
                    {
                      "type": "string",
                      "name": "location",
                      "label": "Location",
                      "namespace": [
                        "page",
                        "blocks",
                        "events",
                        "items",
                        "location"
                      ]
                    }
                  ],
                  "namespace": [
                    "page",
                    "blocks",
                    "events",
                    "items"
                  ],
                  "searchable": true,
                  "uid": false
                }
              ],
              "namespace": [
                "page",
                "blocks",
                "events"
              ]
            },
            {
              "name": "contact",
              "label": "Contact Info",
              "fields": [
                {
                  "type": "string",
                  "name": "address",
                  "label": "Address",
                  "namespace": [
                    "page",
                    "blocks",
                    "contact",
                    "address"
                  ],
                  "searchable": true,
                  "uid": false
                },
                {
                  "type": "string",
                  "name": "phone",
                  "label": "Phone",
                  "namespace": [
                    "page",
                    "blocks",
                    "contact",
                    "phone"
                  ],
                  "searchable": true,
                  "uid": false
                },
                {
                  "type": "string",
                  "name": "email",
                  "label": "Email",
                  "namespace": [
                    "page",
                    "blocks",
                    "contact",
                    "email"
                  ],
                  "searchable": true,
                  "uid": false
                },
                {
                  "type": "string",
                  "name": "mapEmbed",
                  "label": "Google Maps Embed URL",
                  "namespace": [
                    "page",
                    "blocks",
                    "contact",
                    "mapEmbed"
                  ],
                  "searchable": true,
                  "uid": false
                }
              ],
              "namespace": [
                "page",
                "blocks",
                "contact"
              ]
            }
          ],
          "namespace": [
            "page",
            "blocks"
          ],
          "searchable": true,
          "uid": false
        }
      ],
      "namespace": [
        "page"
      ]
    },
    {
      "name": "global",
      "label": "Global Settings",
      "path": "content/global",
      "format": "json",
      "ui": {
        "global": true,
        "allowedActions": {
          "create": false,
          "delete": false
        }
      },
      "fields": [
        {
          "type": "string",
          "name": "brandColor",
          "label": "Brand Color (Hex)",
          "ui": {
            "component": "color"
          },
          "namespace": [
            "global",
            "brandColor"
          ],
          "searchable": true,
          "uid": false
        },
        {
          "type": "image",
          "name": "logo",
          "label": "Logo",
          "namespace": [
            "global",
            "logo"
          ],
          "searchable": false,
          "uid": false
        },
        {
          "type": "boolean",
          "name": "showPlaceholderLogo",
          "label": "Show Placeholder Logo",
          "description": "If no logo is uploaded, show the default 'LC' icon?",
          "ui": {
            "defaultValue": true
          },
          "namespace": [
            "global",
            "showPlaceholderLogo"
          ],
          "searchable": true,
          "uid": false
        },
        {
          "type": "image",
          "name": "favicon",
          "label": "Favicon (Optional)",
          "description": "Upload a square image (PNG/ICO/SVG) to use as the browser icon.",
          "namespace": [
            "global",
            "favicon"
          ],
          "searchable": false,
          "uid": false
        },
        {
          "type": "string",
          "name": "organizationName",
          "label": "Organization Name",
          "namespace": [
            "global",
            "organizationName"
          ],
          "searchable": true,
          "uid": false
        },
        {
          "type": "string",
          "name": "slogan",
          "label": "Footer Slogan",
          "description": "Short text below the logo",
          "namespace": [
            "global",
            "slogan"
          ],
          "searchable": true,
          "uid": false
        },
        {
          "type": "object",
          "list": true,
          "name": "navigation",
          "label": "Navigation",
          "ui": {},
          "fields": [
            {
              "type": "string",
              "name": "label",
              "label": "Label",
              "namespace": [
                "global",
                "navigation",
                "label"
              ],
              "searchable": true,
              "uid": false
            },
            {
              "type": "string",
              "name": "url",
              "label": "URL",
              "namespace": [
                "global",
                "navigation",
                "url"
              ],
              "searchable": true,
              "uid": false
            }
          ],
          "namespace": [
            "global",
            "navigation"
          ],
          "searchable": true,
          "uid": false
        },
        {
          "type": "object",
          "name": "social",
          "label": "Social Links",
          "fields": [
            {
              "type": "string",
              "name": "facebook",
              "label": "Facebook URL",
              "namespace": [
                "global",
                "social",
                "facebook"
              ],
              "searchable": true,
              "uid": false
            },
            {
              "type": "string",
              "name": "instagram",
              "label": "Instagram URL",
              "namespace": [
                "global",
                "social",
                "instagram"
              ],
              "searchable": true,
              "uid": false
            }
          ],
          "namespace": [
            "global",
            "social"
          ],
          "searchable": true,
          "uid": false
        }
      ],
      "namespace": [
        "global"
      ]
    }
  ],
  "config": {
    "media": {
      "tina": {
        "publicFolder": "public",
        "mediaRoot": "uploads"
      }
    }
  }
}